hid1kbrute/__init__.py
hid1kbrute/analyzer.py
hid1kbrute/display.py
hid1kbrute/models.py
hid1kbrute/py1kbrute.py
hid1kbrute/py1kencoder.py
hid1kbrute/utils.py
hid1kbrute-0.1.2.dist-info/METADATA
hid1kbrute-0.1.2.dist-info/WHEEL
hid1kbrute-0.1.2.dist-info/entry_points.txt
hid1kbrute-0.1.2.dist-info/top_level.txt
hid1kbrute-0.1.2.dist-info/RECORD
