Metadata-Version: 2.4
Name: hid1kbrute
Version: 0.1.2
Summary: A tool for analyzing and brute-forcing HID 1K cards
Author-email: "T.I. (aka cmdpirx)" <cmdpirx@protonmail.com>
License-Expression: MIT
